MANIFEST.in
README.md
setup.py
bin/gst-make
gst_make/__init__.py
gst_make.egg-info/PKG-INFO
gst_make.egg-info/SOURCES.txt
gst_make.egg-info/dependency_links.txt
gst_make.egg-info/not-zip-safe
gst_make.egg-info/top_level.txt
gst_make/scripts/gst-make-element
gst_make/scripts/gst-make-indent
gst_make/scripts/gst-make-plugin
gst_make/scripts/gst-make-project
gst_make/templates/.DS_Store
gst_make/templates/elements/audiodecoder
gst_make/templates/elements/audioencoder
gst_make/templates/elements/audiofilter
gst_make/templates/elements/audiosink
gst_make/templates/elements/audiosrc
gst_make/templates/elements/baseparse
gst_make/templates/elements/basesink
gst_make/templates/elements/basesrc
gst_make/templates/elements/basetransform
gst_make/templates/elements/element
gst_make/templates/elements/gobject
gst_make/templates/elements/sinkpad
gst_make/templates/elements/sinkpad-audio
gst_make/templates/elements/sinkpad-simple
gst_make/templates/elements/sinkpad-template
gst_make/templates/elements/sinkpad-template-video
gst_make/templates/elements/srcpad
gst_make/templates/elements/srcpad-audio
gst_make/templates/elements/srcpad-simple
gst_make/templates/elements/srcpad-template
gst_make/templates/elements/srcpad-template-video
gst_make/templates/elements/videodecoder
gst_make/templates/elements/videoencoder
gst_make/templates/elements/videofilter
gst_make/templates/elements/videosink
gst_make/templates/project/.gitignore
gst_make/templates/project/README.md
gst_make/templates/project/meson.build
gst_make/templates/project/gst/meson.build
gst_make/templates/project/gst-libs/meson.build
gst_make/templates/project/tests/gsttest.c
gst_make/templates/project/tests/meson.build