Metadata-Version: 1.0
Name: gst-make
Version: 0.0.2
Summary: Set of tools for building gstreamer plugins
Home-page: https://github.com/ast/gst-make
Author: Albin Stigo
Author-email: albin.stigo@gmail.com
License: LGPL
Platform: UNKNOWN
